twitter.common.python-0.7.0-py2.7-nspkg.pth
twitter/common/python/__init__.py
twitter/common/python/base.py
twitter/common/python/common.py
twitter/common/python/compatibility.py
twitter/common/python/environment.py
twitter/common/python/fetcher.py
twitter/common/python/finders.py
twitter/common/python/installer.py
twitter/common/python/interpreter.py
twitter/common/python/marshaller.py
twitter/common/python/obtainer.py
twitter/common/python/orderedset.py
twitter/common/python/package.py
twitter/common/python/pep425.py
twitter/common/python/pex.py
twitter/common/python/pex_bootstrapper.py
twitter/common/python/pex_builder.py
twitter/common/python/pex_info.py
twitter/common/python/platforms.py
twitter/common/python/resolver.py
twitter/common/python/testing.py
twitter/common/python/tracer.py
twitter/common/python/translator.py
twitter/common/python/util.py
twitter/common/python/http/__init__.py
twitter/common/python/http/crawler.py
twitter/common/python/http/http.py
twitter/common/python/http/link.py
twitter/common/python/http/tracer.py
twitter.common.python-0.7.0.dist-info/DESCRIPTION.rst
twitter.common.python-0.7.0.dist-info/METADATA
twitter.common.python-0.7.0.dist-info/RECORD
twitter.common.python-0.7.0.dist-info/WHEEL
twitter.common.python-0.7.0.dist-info/metadata.json
twitter.common.python-0.7.0.dist-info/namespace_packages.txt
twitter.common.python-0.7.0.dist-info/top_level.txt
twitter.common.python-0.7.0.dist-info/zip-safe
