Metadata-Version: 2.0
Name: twitter.common.python
Version: 0.7.0
Summary: Twitter's Python packaging toolchain.
Home-page: https://github.com/twitter/commons/tree/master/src/python/twitter/common/python
Author: UNKNOWN
Author-email: UNKNOWN
License: Apache License, Version 2.0
Platform: UNKNOWN
Classifier: Intended Audience :: Developers
Classifier: License :: OSI Approved :: Apache Software License
Classifier: Operating System :: OS Independent
Classifier: Programming Language :: Python
Requires-Dist: pex (==0.7.0)
